matematica/__init__.py
matematica/aritmetica.py
matematica/geometria.py
davidflmatematica-0.1.dist-info/LICENSE.txt
davidflmatematica-0.1.dist-info/METADATA
davidflmatematica-0.1.dist-info/WHEEL
davidflmatematica-0.1.dist-info/top_level.txt
davidflmatematica-0.1.dist-info/RECORD
